README.md
setup.cfg
setup.py
mlmr/__init__.py
mlmr/function.py
mlmr/transformers.py
mlmr.egg-info/PKG-INFO
mlmr.egg-info/SOURCES.txt
mlmr.egg-info/dependency_links.txt
mlmr.egg-info/requires.txt
mlmr.egg-info/top_level.txt
mlmr/test/__init__.py
mlmr/test/test_function.py