Metadata-Version: 2.1
Name: mlmr
Version: 1.0.0
Summary: This library will help you easily parallelize your python code for all kind of data transformations.
Home-page: https://github.com/mbalatsko/mlmr
Author: Maksym Balatsko
Author-email: mbalatsko@gmail.com
License: MIT License
Download-URL: https://github.com/mbalatsko/mlmr/archive/1.0.0.tar.gz
Keywords: mapreduce,parallel,transformation,ml,pandas
Platform: UNKNOWN
Classifier: Programming Language :: Python :: 3
Classifier: Programming Language :: Python :: 3.0
Classifier: Programming Language :: Python :: 3.1
Classifier: Programming Language :: Python :: 3.2
Classifier: Programming Language :: Python :: 3.3
Classifier: Programming Language :: Python :: 3.4
Classifier: Programming Language :: Python :: 3.5
Classifier: Programming Language :: Python :: 3.6
Classifier: Programming Language :: Python :: 3.7
Classifier: Operating System :: OS Independent
